main.py
PyWorkout-1.2.0.dist-info/LICENSE.md
PyWorkout-1.2.0.dist-info/METADATA
PyWorkout-1.2.0.dist-info/WHEEL
PyWorkout-1.2.0.dist-info/entry_points.txt
PyWorkout-1.2.0.dist-info/top_level.txt
PyWorkout-1.2.0.dist-info/RECORD
