Metadata-Version: 2.1
Name: PyWorkout
Version: 1.2.0
Summary: A minimal CLI to keep you inspired during your workout!
Home-page: https://github.com/Dog-Face-Development/PyWorkout
Author: willtheorangeguy
License: # GNU GENERAL PUBLIC LICENSE        
Project-URL: Homepage, https://github.com/Dog-Face-Development/PyWorkout
Project-URL: Bug Tracker, https://github.com/Dog-Face-Development/PyWorkout/issues
Keywords: workout plan tracking tracker video cli
Classifier: Development Status :: 5 - Production/Stable
Classifier: License :: OSI Approved :: GNU General Public License v3 (GPLv3)
Classifier: Natural Language :: English
Classifier: Operating System :: OS Independent
Classifier: Topic :: Other/Nonlisted Topic
Requires-Python: >=3.9
License-File: LICENSE.md
